[
  {
    "date": "2026-03-06",
    "type": "daily",
    "generated": "2026-03-08T07:37:50.494364",
    "twitter": "\ud83d\udfe2 APEX TRADE LAB Daily Signal \u2014 2026-03-06\n\nRegime: STRONG UPTREND\nAction: Light long TQQQ (8%)\n\nTQQQ: 8% | SQQQ: 0% | Cash: 92%\nNDX: 24,643 | RSI: 43\n\nPaper trading simulation \u2014 not financial advice.\n#TQQQ #SQQQ #AlgoTrading #SystematicTrading #PaperTrading",
    "facebook": "\u26a1 APEX TRADE LAB \u2014 Daily Signal Update\n\ud83d\udcc5 2026-03-06\n\n\ud83d\udfe2 Market Regime: STRONG UPTREND\n\ud83d\udcca Action: Light long TQQQ (8%)\n\nPortfolio Allocation:\n  \u2022 TQQQ (3x Long): 8%\n  \u2022 SQQQ (3x Short): 0%\n  \u2022 Cash: 92%\n\nNDX closed at 24,643 | RSI: 43\n\nThis is a paper trading simulation for educational purposes.\nFull dashboard: [link in bio]\n\n#TQQQ #SQQQ #AlgoTrading #SystematicTrading #PaperTrading",
    "telegram": "\u26a1 <b>APEX TRADE LAB</b> \u2014 2026-03-06\n\n\ud83d\udfe2 <b>STRONG UPTREND</b>\nAction: Light long TQQQ (8%)\n\nTQQQ: 8% | SQQQ: 0% | Cash: 92%\nNDX: 24,643 | RSI: 43\n\n<i>Paper trading only \u2014 not advice.</i>",
    "discord": "\ud83d\udfe2 APEX TRADE LAB Daily Signal \u2014 2026-03-06\n\nRegime: STRONG UPTREND\nAction: Light long TQQQ (8%)\n\nTQQQ: 8% | SQQQ: 0% | Cash: 92%\nNDX: 24,643 | RSI: 43\n\nPaper trading simulation \u2014 not financial advice.\n#TQQQ #SQQQ #AlgoTrading #SystematicTrading #PaperTrading"
  },
  {
    "date": "2026-03-09",
    "type": "daily",
    "generated": "2026-03-10T21:58:01.700995",
    "twitter": "\ud83d\udfe2 APEX TRADE LAB Daily Signal \u2014 2026-03-09\n\nRegime: STRONG UPTREND\nAction: Light long TQQQ (20%)\n\nTQQQ: 20% | SQQQ: 0% | Cash: 80%\nNDX: 24,967 | RSI: 49\n\nPaper trading simulation \u2014 not financial advice.\n#TQQQ #SQQQ #AlgoTrading #SystematicTrading #PaperTrading",
    "facebook": "\u26a1 APEX TRADE LAB \u2014 Daily Signal Update\n\ud83d\udcc5 2026-03-09\n\n\ud83d\udfe2 Market Regime: STRONG UPTREND\n\ud83d\udcca Action: Light long TQQQ (20%)\n\nPortfolio Allocation:\n  \u2022 TQQQ (3x Long): 20%\n  \u2022 SQQQ (3x Short): 0%\n  \u2022 Cash: 80%\n\nNDX closed at 24,967 | RSI: 49\n\nThis is a paper trading simulation for educational purposes.\nFull dashboard: [link in bio]\n\n#TQQQ #SQQQ #AlgoTrading #SystematicTrading #PaperTrading",
    "telegram": "\u26a1 <b>APEX TRADE LAB</b> \u2014 2026-03-09\n\n\ud83d\udfe2 <b>STRONG UPTREND</b>\nAction: Light long TQQQ (20%)\n\nTQQQ: 20% | SQQQ: 0% | Cash: 80%\nNDX: 24,967 | RSI: 49\n\n<i>Paper trading only \u2014 not advice.</i>",
    "discord": "\ud83d\udfe2 APEX TRADE LAB Daily Signal \u2014 2026-03-09\n\nRegime: STRONG UPTREND\nAction: Light long TQQQ (20%)\n\nTQQQ: 20% | SQQQ: 0% | Cash: 80%\nNDX: 24,967 | RSI: 49\n\nPaper trading simulation \u2014 not financial advice.\n#TQQQ #SQQQ #AlgoTrading #SystematicTrading #PaperTrading"
  },
  {
    "date": "2026-03-10",
    "type": "daily",
    "generated": "2026-03-11T22:02:18.877808",
    "twitter": "\ud83d\udfe2 APEX TRADE LAB Daily Signal \u2014 2026-03-10\n\nRegime: STRONG UPTREND\nAction: Light long TQQQ (20%)\n\nTQQQ: 20% | SQQQ: 0% | Cash: 80%\nNDX: 24,956 | RSI: 49\n\nPaper trading simulation \u2014 not financial advice.\n#TQQQ #SQQQ #AlgoTrading #SystematicTrading #PaperTrading",
    "facebook": "\u26a1 APEX TRADE LAB \u2014 Daily Signal Update\n\ud83d\udcc5 2026-03-10\n\n\ud83d\udfe2 Market Regime: STRONG UPTREND\n\ud83d\udcca Action: Light long TQQQ (20%)\n\nPortfolio Allocation:\n  \u2022 TQQQ (3x Long): 20%\n  \u2022 SQQQ (3x Short): 0%\n  \u2022 Cash: 80%\n\nNDX closed at 24,956 | RSI: 49\n\nThis is a paper trading simulation for educational purposes.\nFull dashboard: [link in bio]\n\n#TQQQ #SQQQ #AlgoTrading #SystematicTrading #PaperTrading",
    "telegram": "\u26a1 <b>APEX TRADE LAB</b> \u2014 2026-03-10\n\n\ud83d\udfe2 <b>STRONG UPTREND</b>\nAction: Light long TQQQ (20%)\n\nTQQQ: 20% | SQQQ: 0% | Cash: 80%\nNDX: 24,956 | RSI: 49\n\n<i>Paper trading only \u2014 not advice.</i>",
    "discord": "\ud83d\udfe2 APEX TRADE LAB Daily Signal \u2014 2026-03-10\n\nRegime: STRONG UPTREND\nAction: Light long TQQQ (20%)\n\nTQQQ: 20% | SQQQ: 0% | Cash: 80%\nNDX: 24,956 | RSI: 49\n\nPaper trading simulation \u2014 not financial advice.\n#TQQQ #SQQQ #AlgoTrading #SystematicTrading #PaperTrading"
  },
  {
    "date": "2026-03-11",
    "type": "daily",
    "generated": "2026-03-12T22:02:14.828082",
    "twitter": "\ud83d\udfe2 APEX TRADE LAB Daily Signal \u2014 2026-03-11\n\nRegime: STRONG UPTREND\nAction: Light long TQQQ (20%)\n\nTQQQ: 20% | SQQQ: 0% | Cash: 80%\nNDX: 24,965 | RSI: 49\n\nPaper trading simulation \u2014 not financial advice.\n#TQQQ #SQQQ #AlgoTrading #SystematicTrading #PaperTrading",
    "facebook": "\u26a1 APEX TRADE LAB \u2014 Daily Signal Update\n\ud83d\udcc5 2026-03-11\n\n\ud83d\udfe2 Market Regime: STRONG UPTREND\n\ud83d\udcca Action: Light long TQQQ (20%)\n\nPortfolio Allocation:\n  \u2022 TQQQ (3x Long): 20%\n  \u2022 SQQQ (3x Short): 0%\n  \u2022 Cash: 80%\n\nNDX closed at 24,965 | RSI: 49\n\nThis is a paper trading simulation for educational purposes.\nFull dashboard: [link in bio]\n\n#TQQQ #SQQQ #AlgoTrading #SystematicTrading #PaperTrading",
    "telegram": "\u26a1 <b>APEX TRADE LAB</b> \u2014 2026-03-11\n\n\ud83d\udfe2 <b>STRONG UPTREND</b>\nAction: Light long TQQQ (20%)\n\nTQQQ: 20% | SQQQ: 0% | Cash: 80%\nNDX: 24,965 | RSI: 49\n\n<i>Paper trading only \u2014 not advice.</i>",
    "discord": "\ud83d\udfe2 APEX TRADE LAB Daily Signal \u2014 2026-03-11\n\nRegime: STRONG UPTREND\nAction: Light long TQQQ (20%)\n\nTQQQ: 20% | SQQQ: 0% | Cash: 80%\nNDX: 24,965 | RSI: 49\n\nPaper trading simulation \u2014 not financial advice.\n#TQQQ #SQQQ #AlgoTrading #SystematicTrading #PaperTrading"
  },
  {
    "date": "2026-03-12",
    "type": "daily",
    "generated": "2026-03-13T22:03:20.932012",
    "twitter": "\ud83d\udfe2 APEX TRADE LAB Daily Signal \u2014 2026-03-12\n\nRegime: STRONG UPTREND\nAction: Light long TQQQ (8%)\n\nTQQQ: 8% | SQQQ: 0% | Cash: 92%\nNDX: 24,534 | RSI: 42\n\nPaper trading simulation \u2014 not financial advice.\n#TQQQ #SQQQ #AlgoTrading #SystematicTrading #PaperTrading",
    "facebook": "\u26a1 APEX TRADE LAB \u2014 Daily Signal Update\n\ud83d\udcc5 2026-03-12\n\n\ud83d\udfe2 Market Regime: STRONG UPTREND\n\ud83d\udcca Action: Light long TQQQ (8%)\n\nPortfolio Allocation:\n  \u2022 TQQQ (3x Long): 8%\n  \u2022 SQQQ (3x Short): 0%\n  \u2022 Cash: 92%\n\nNDX closed at 24,534 | RSI: 42\n\nThis is a paper trading simulation for educational purposes.\nFull dashboard: [link in bio]\n\n#TQQQ #SQQQ #AlgoTrading #SystematicTrading #PaperTrading",
    "telegram": "\u26a1 <b>APEX TRADE LAB</b> \u2014 2026-03-12\n\n\ud83d\udfe2 <b>STRONG UPTREND</b>\nAction: Light long TQQQ (8%)\n\nTQQQ: 8% | SQQQ: 0% | Cash: 92%\nNDX: 24,534 | RSI: 42\n\n<i>Paper trading only \u2014 not advice.</i>",
    "discord": "\ud83d\udfe2 APEX TRADE LAB Daily Signal \u2014 2026-03-12\n\nRegime: STRONG UPTREND\nAction: Light long TQQQ (8%)\n\nTQQQ: 8% | SQQQ: 0% | Cash: 92%\nNDX: 24,534 | RSI: 42\n\nPaper trading simulation \u2014 not financial advice.\n#TQQQ #SQQQ #AlgoTrading #SystematicTrading #PaperTrading"
  },
  {
    "date": "2026-03-13",
    "type": "weekly",
    "generated": "2026-03-13T22:03:20.932056",
    "twitter": "\ud83d\udcc8 APEX TRADE LAB \u2014 Weekly P&L\nWeek ending 2026-03-13\n\nWeekly: $+568 (+0.6%)\nTotal Return: -3.2%\nPortfolio: $96,746\nTrades this week: 3\n\nPaper trading sim \u2014 not advice.\n#TQQQ #SQQQ #AlgoTrading #SystematicTrading #PaperTrading",
    "facebook": "\ud83d\udcca APEX TRADE LAB \u2014 Weekly Performance Report\nWeek ending 2026-03-13\n\n\ud83d\udcc8 This Week: $+568 (+0.6%)\n\ud83d\udcb0 Portfolio Value: $96,746\n\ud83d\udcc8 Total Return: -3.2%\n\ud83d\udd04 Trades Executed: 3\n\nThe system traded conservatively this week.\n\nFull analysis: [link in bio]\n\nPaper trading simulation \u2014 educational purposes only.\n#TQQQ #SQQQ #AlgoTrading #SystematicTrading #PaperTrading",
    "telegram": "\ud83d\udcc8 APEX TRADE LAB \u2014 Weekly P&L\nWeek ending 2026-03-13\n\nWeekly: $+568 (+0.6%)\nTotal Return: -3.2%\nPortfolio: $96,746\nTrades this week: 3\n\nPaper trading sim \u2014 not advice.\n#TQQQ #SQQQ #AlgoTrading #SystematicTrading #PaperTrading",
    "discord": "\ud83d\udcc8 APEX TRADE LAB \u2014 Weekly P&L\nWeek ending 2026-03-13\n\nWeekly: $+568 (+0.6%)\nTotal Return: -3.2%\nPortfolio: $96,746\nTrades this week: 3\n\nPaper trading sim \u2014 not advice.\n#TQQQ #SQQQ #AlgoTrading #SystematicTrading #PaperTrading"
  },
  {
    "date": "2026-03-13",
    "type": "daily",
    "generated": "2026-03-16T22:57:56.499987",
    "twitter": "\ud83d\udfe2 APEX TRADE LAB Daily Signal \u2014 2026-03-13\n\nRegime: UPTREND\nAction: Light long TQQQ (12%)\n\nTQQQ: 12% | SQQQ: 0% | Cash: 88%\nNDX: 24,381 | RSI: 40\n\nPaper trading simulation \u2014 not financial advice.\n#TQQQ #SQQQ #AlgoTrading #SystematicTrading #PaperTrading",
    "facebook": "\u26a1 APEX TRADE LAB \u2014 Daily Signal Update\n\ud83d\udcc5 2026-03-13\n\n\ud83d\udfe2 Market Regime: UPTREND\n\ud83d\udcca Action: Light long TQQQ (12%)\n\nPortfolio Allocation:\n  \u2022 TQQQ (3x Long): 12%\n  \u2022 SQQQ (3x Short): 0%\n  \u2022 Cash: 88%\n\nNDX closed at 24,381 | RSI: 40\n\nThis is a paper trading simulation for educational purposes.\nFull dashboard: [link in bio]\n\n#TQQQ #SQQQ #AlgoTrading #SystematicTrading #PaperTrading",
    "telegram": "\u26a1 <b>APEX TRADE LAB</b> \u2014 2026-03-13\n\n\ud83d\udfe2 <b>UPTREND</b>\nAction: Light long TQQQ (12%)\n\nTQQQ: 12% | SQQQ: 0% | Cash: 88%\nNDX: 24,381 | RSI: 40\n\n<i>Paper trading only \u2014 not advice.</i>",
    "discord": "\ud83d\udfe2 APEX TRADE LAB Daily Signal \u2014 2026-03-13\n\nRegime: UPTREND\nAction: Light long TQQQ (12%)\n\nTQQQ: 12% | SQQQ: 0% | Cash: 88%\nNDX: 24,381 | RSI: 40\n\nPaper trading simulation \u2014 not financial advice.\n#TQQQ #SQQQ #AlgoTrading #SystematicTrading #PaperTrading"
  },
  {
    "date": "2026-03-16",
    "type": "daily",
    "generated": "2026-03-17T23:03:10.818551",
    "twitter": "\ud83d\udfe2 APEX TRADE LAB Daily Signal \u2014 2026-03-16\n\nRegime: STRONG UPTREND\nAction: Light long TQQQ (37%)\n\nTQQQ: 37% | SQQQ: 0% | Cash: 63%\nNDX: 24,655 | RSI: 45\n\nPaper trading simulation \u2014 not financial advice.\n#TQQQ #SQQQ #AlgoTrading #SystematicTrading #PaperTrading",
    "facebook": "\u26a1 APEX TRADE LAB \u2014 Daily Signal Update\n\ud83d\udcc5 2026-03-16\n\n\ud83d\udfe2 Market Regime: STRONG UPTREND\n\ud83d\udcca Action: Light long TQQQ (37%)\n\nPortfolio Allocation:\n  \u2022 TQQQ (3x Long): 37%\n  \u2022 SQQQ (3x Short): 0%\n  \u2022 Cash: 63%\n\nNDX closed at 24,655 | RSI: 45\n\nThis is a paper trading simulation for educational purposes.\nFull dashboard: [link in bio]\n\n#TQQQ #SQQQ #AlgoTrading #SystematicTrading #PaperTrading",
    "telegram": "\u26a1 <b>APEX TRADE LAB</b> \u2014 2026-03-16\n\n\ud83d\udfe2 <b>STRONG UPTREND</b>\nAction: Light long TQQQ (37%)\n\nTQQQ: 37% | SQQQ: 0% | Cash: 63%\nNDX: 24,655 | RSI: 45\n\n<i>Paper trading only \u2014 not advice.</i>",
    "discord": "\ud83d\udfe2 APEX TRADE LAB Daily Signal \u2014 2026-03-16\n\nRegime: STRONG UPTREND\nAction: Light long TQQQ (37%)\n\nTQQQ: 37% | SQQQ: 0% | Cash: 63%\nNDX: 24,655 | RSI: 45\n\nPaper trading simulation \u2014 not financial advice.\n#TQQQ #SQQQ #AlgoTrading #SystematicTrading #PaperTrading"
  },
  {
    "date": "2026-03-17",
    "type": "daily",
    "generated": "2026-03-18T22:57:10.318849",
    "twitter": "\ud83d\udfe2 APEX TRADE LAB Daily Signal \u2014 2026-03-17\n\nRegime: STRONG UPTREND\nAction: Light long TQQQ (27%)\n\nTQQQ: 27% | SQQQ: 0% | Cash: 73%\nNDX: 24,780 | RSI: 47\n\nPaper trading simulation \u2014 not financial advice.\n#TQQQ #SQQQ #AlgoTrading #SystematicTrading #PaperTrading",
    "facebook": "\u26a1 APEX TRADE LAB \u2014 Daily Signal Update\n\ud83d\udcc5 2026-03-17\n\n\ud83d\udfe2 Market Regime: STRONG UPTREND\n\ud83d\udcca Action: Light long TQQQ (27%)\n\nPortfolio Allocation:\n  \u2022 TQQQ (3x Long): 27%\n  \u2022 SQQQ (3x Short): 0%\n  \u2022 Cash: 73%\n\nNDX closed at 24,780 | RSI: 47\n\nThis is a paper trading simulation for educational purposes.\nFull dashboard: [link in bio]\n\n#TQQQ #SQQQ #AlgoTrading #SystematicTrading #PaperTrading",
    "telegram": "\u26a1 <b>APEX TRADE LAB</b> \u2014 2026-03-17\n\n\ud83d\udfe2 <b>STRONG UPTREND</b>\nAction: Light long TQQQ (27%)\n\nTQQQ: 27% | SQQQ: 0% | Cash: 73%\nNDX: 24,780 | RSI: 47\n\n<i>Paper trading only \u2014 not advice.</i>",
    "discord": "\ud83d\udfe2 APEX TRADE LAB Daily Signal \u2014 2026-03-17\n\nRegime: STRONG UPTREND\nAction: Light long TQQQ (27%)\n\nTQQQ: 27% | SQQQ: 0% | Cash: 73%\nNDX: 24,780 | RSI: 47\n\nPaper trading simulation \u2014 not financial advice.\n#TQQQ #SQQQ #AlgoTrading #SystematicTrading #PaperTrading"
  },
  {
    "date": "2026-03-18",
    "type": "daily",
    "generated": "2026-03-19T22:02:12.662320",
    "twitter": "\ud83d\udfe2 APEX TRADE LAB Daily Signal \u2014 2026-03-18\n\nRegime: UPTREND\nAction: Light long TQQQ (8%)\n\nTQQQ: 8% | SQQQ: 0% | Cash: 92%\nNDX: 24,425 | RSI: 42\n\nPaper trading simulation \u2014 not financial advice.\n#TQQQ #SQQQ #AlgoTrading #SystematicTrading #PaperTrading",
    "facebook": "\u26a1 APEX TRADE LAB \u2014 Daily Signal Update\n\ud83d\udcc5 2026-03-18\n\n\ud83d\udfe2 Market Regime: UPTREND\n\ud83d\udcca Action: Light long TQQQ (8%)\n\nPortfolio Allocation:\n  \u2022 TQQQ (3x Long): 8%\n  \u2022 SQQQ (3x Short): 0%\n  \u2022 Cash: 92%\n\nNDX closed at 24,425 | RSI: 42\n\nThis is a paper trading simulation for educational purposes.\nFull dashboard: [link in bio]\n\n#TQQQ #SQQQ #AlgoTrading #SystematicTrading #PaperTrading",
    "telegram": "\u26a1 <b>APEX TRADE LAB</b> \u2014 2026-03-18\n\n\ud83d\udfe2 <b>UPTREND</b>\nAction: Light long TQQQ (8%)\n\nTQQQ: 8% | SQQQ: 0% | Cash: 92%\nNDX: 24,425 | RSI: 42\n\n<i>Paper trading only \u2014 not advice.</i>",
    "discord": "\ud83d\udfe2 APEX TRADE LAB Daily Signal \u2014 2026-03-18\n\nRegime: UPTREND\nAction: Light long TQQQ (8%)\n\nTQQQ: 8% | SQQQ: 0% | Cash: 92%\nNDX: 24,425 | RSI: 42\n\nPaper trading simulation \u2014 not financial advice.\n#TQQQ #SQQQ #AlgoTrading #SystematicTrading #PaperTrading"
  },
  {
    "date": "2026-03-19",
    "type": "daily",
    "generated": "2026-03-20T22:00:55.059458",
    "twitter": "\ud83d\udfe2 APEX TRADE LAB Daily Signal \u2014 2026-03-19\n\nRegime: UPTREND\nAction: Light long TQQQ (8%)\n\nTQQQ: 8% | SQQQ: 0% | Cash: 92%\nNDX: 24,355 | RSI: 41\n\nPaper trading simulation \u2014 not financial advice.\n#TQQQ #SQQQ #AlgoTrading #SystematicTrading #PaperTrading",
    "facebook": "\u26a1 APEX TRADE LAB \u2014 Daily Signal Update\n\ud83d\udcc5 2026-03-19\n\n\ud83d\udfe2 Market Regime: UPTREND\n\ud83d\udcca Action: Light long TQQQ (8%)\n\nPortfolio Allocation:\n  \u2022 TQQQ (3x Long): 8%\n  \u2022 SQQQ (3x Short): 0%\n  \u2022 Cash: 92%\n\nNDX closed at 24,355 | RSI: 41\n\nThis is a paper trading simulation for educational purposes.\nFull dashboard: [link in bio]\n\n#TQQQ #SQQQ #AlgoTrading #SystematicTrading #PaperTrading",
    "telegram": "\u26a1 <b>APEX TRADE LAB</b> \u2014 2026-03-19\n\n\ud83d\udfe2 <b>UPTREND</b>\nAction: Light long TQQQ (8%)\n\nTQQQ: 8% | SQQQ: 0% | Cash: 92%\nNDX: 24,355 | RSI: 41\n\n<i>Paper trading only \u2014 not advice.</i>",
    "discord": "\ud83d\udfe2 APEX TRADE LAB Daily Signal \u2014 2026-03-19\n\nRegime: UPTREND\nAction: Light long TQQQ (8%)\n\nTQQQ: 8% | SQQQ: 0% | Cash: 92%\nNDX: 24,355 | RSI: 41\n\nPaper trading simulation \u2014 not financial advice.\n#TQQQ #SQQQ #AlgoTrading #SystematicTrading #PaperTrading"
  },
  {
    "date": "2026-03-20",
    "type": "weekly",
    "generated": "2026-03-20T22:00:55.059504",
    "twitter": "\ud83d\udcc8 APEX TRADE LAB \u2014 Weekly P&L\nWeek ending 2026-03-20\n\nWeekly: $+221 (+0.2%)\nTotal Return: -3.4%\nPortfolio: $96,616\nTrades this week: 3\n\nPaper trading sim \u2014 not advice.\n#TQQQ #SQQQ #AlgoTrading #SystematicTrading #PaperTrading",
    "facebook": "\ud83d\udcca APEX TRADE LAB \u2014 Weekly Performance Report\nWeek ending 2026-03-20\n\n\ud83d\udcc8 This Week: $+221 (+0.2%)\n\ud83d\udcb0 Portfolio Value: $96,616\n\ud83d\udcc8 Total Return: -3.4%\n\ud83d\udd04 Trades Executed: 3\n\nThe system traded conservatively this week.\n\nFull analysis: [link in bio]\n\nPaper trading simulation \u2014 educational purposes only.\n#TQQQ #SQQQ #AlgoTrading #SystematicTrading #PaperTrading",
    "telegram": "\ud83d\udcc8 APEX TRADE LAB \u2014 Weekly P&L\nWeek ending 2026-03-20\n\nWeekly: $+221 (+0.2%)\nTotal Return: -3.4%\nPortfolio: $96,616\nTrades this week: 3\n\nPaper trading sim \u2014 not advice.\n#TQQQ #SQQQ #AlgoTrading #SystematicTrading #PaperTrading",
    "discord": "\ud83d\udcc8 APEX TRADE LAB \u2014 Weekly P&L\nWeek ending 2026-03-20\n\nWeekly: $+221 (+0.2%)\nTotal Return: -3.4%\nPortfolio: $96,616\nTrades this week: 3\n\nPaper trading sim \u2014 not advice.\n#TQQQ #SQQQ #AlgoTrading #SystematicTrading #PaperTrading"
  },
  {
    "date": "2026-03-20",
    "type": "daily",
    "generated": "2026-03-23T23:02:50.591372",
    "twitter": "\ud83d\udfe2 APEX TRADE LAB Daily Signal \u2014 2026-03-20\n\nRegime: UPTREND\nAction: Light long TQQQ (22%)\n\nTQQQ: 22% | SQQQ: 0% | Cash: 78%\nNDX: 23,898 | RSI: 35\n\nPaper trading simulation \u2014 not financial advice.\n#TQQQ #SQQQ #AlgoTrading #SystematicTrading #PaperTrading",
    "facebook": "\u26a1 APEX TRADE LAB \u2014 Daily Signal Update\n\ud83d\udcc5 2026-03-20\n\n\ud83d\udfe2 Market Regime: UPTREND\n\ud83d\udcca Action: Light long TQQQ (22%)\n\nPortfolio Allocation:\n  \u2022 TQQQ (3x Long): 22%\n  \u2022 SQQQ (3x Short): 0%\n  \u2022 Cash: 78%\n\nNDX closed at 23,898 | RSI: 35\n\nThis is a paper trading simulation for educational purposes.\nFull dashboard: [link in bio]\n\n#TQQQ #SQQQ #AlgoTrading #SystematicTrading #PaperTrading",
    "telegram": "\u26a1 <b>APEX TRADE LAB</b> \u2014 2026-03-20\n\n\ud83d\udfe2 <b>UPTREND</b>\nAction: Light long TQQQ (22%)\n\nTQQQ: 22% | SQQQ: 0% | Cash: 78%\nNDX: 23,898 | RSI: 35\n\n<i>Paper trading only \u2014 not advice.</i>",
    "discord": "\ud83d\udfe2 APEX TRADE LAB Daily Signal \u2014 2026-03-20\n\nRegime: UPTREND\nAction: Light long TQQQ (22%)\n\nTQQQ: 22% | SQQQ: 0% | Cash: 78%\nNDX: 23,898 | RSI: 35\n\nPaper trading simulation \u2014 not financial advice.\n#TQQQ #SQQQ #AlgoTrading #SystematicTrading #PaperTrading"
  },
  {
    "date": "2026-03-23",
    "type": "daily",
    "generated": "2026-03-24T23:00:57.798127",
    "twitter": "\ud83d\udfe2 APEX TRADE LAB Daily Signal \u2014 2026-03-23\n\nRegime: UPTREND\nAction: Light long TQQQ (8%)\n\nTQQQ: 8% | SQQQ: 0% | Cash: 92%\nNDX: 24,189 | RSI: 41\n\nPaper trading simulation \u2014 not financial advice.\n#TQQQ #SQQQ #AlgoTrading #SystematicTrading #PaperTrading",
    "facebook": "\u26a1 APEX TRADE LAB \u2014 Daily Signal Update\n\ud83d\udcc5 2026-03-23\n\n\ud83d\udfe2 Market Regime: UPTREND\n\ud83d\udcca Action: Light long TQQQ (8%)\n\nPortfolio Allocation:\n  \u2022 TQQQ (3x Long): 8%\n  \u2022 SQQQ (3x Short): 0%\n  \u2022 Cash: 92%\n\nNDX closed at 24,189 | RSI: 41\n\nThis is a paper trading simulation for educational purposes.\nFull dashboard: [link in bio]\n\n#TQQQ #SQQQ #AlgoTrading #SystematicTrading #PaperTrading",
    "telegram": "\u26a1 <b>APEX TRADE LAB</b> \u2014 2026-03-23\n\n\ud83d\udfe2 <b>UPTREND</b>\nAction: Light long TQQQ (8%)\n\nTQQQ: 8% | SQQQ: 0% | Cash: 92%\nNDX: 24,189 | RSI: 41\n\n<i>Paper trading only \u2014 not advice.</i>",
    "discord": "\ud83d\udfe2 APEX TRADE LAB Daily Signal \u2014 2026-03-23\n\nRegime: UPTREND\nAction: Light long TQQQ (8%)\n\nTQQQ: 8% | SQQQ: 0% | Cash: 92%\nNDX: 24,189 | RSI: 41\n\nPaper trading simulation \u2014 not financial advice.\n#TQQQ #SQQQ #AlgoTrading #SystematicTrading #PaperTrading"
  },
  {
    "date": "2026-03-24",
    "type": "daily",
    "generated": "2026-03-25T23:06:02.996294",
    "twitter": "\ud83d\udfe2 APEX TRADE LAB Daily Signal \u2014 2026-03-24\n\nRegime: UPTREND\nAction: Light long TQQQ (16%)\n\nTQQQ: 16% | SQQQ: 0% | Cash: 84%\nNDX: 24,002 | RSI: 38\n\nPaper trading simulation \u2014 not financial advice.\n#TQQQ #SQQQ #AlgoTrading #SystematicTrading #PaperTrading",
    "facebook": "\u26a1 APEX TRADE LAB \u2014 Daily Signal Update\n\ud83d\udcc5 2026-03-24\n\n\ud83d\udfe2 Market Regime: UPTREND\n\ud83d\udcca Action: Light long TQQQ (16%)\n\nPortfolio Allocation:\n  \u2022 TQQQ (3x Long): 16%\n  \u2022 SQQQ (3x Short): 0%\n  \u2022 Cash: 84%\n\nNDX closed at 24,002 | RSI: 38\n\nThis is a paper trading simulation for educational purposes.\nFull dashboard: [link in bio]\n\n#TQQQ #SQQQ #AlgoTrading #SystematicTrading #PaperTrading",
    "telegram": "\u26a1 <b>APEX TRADE LAB</b> \u2014 2026-03-24\n\n\ud83d\udfe2 <b>UPTREND</b>\nAction: Light long TQQQ (16%)\n\nTQQQ: 16% | SQQQ: 0% | Cash: 84%\nNDX: 24,002 | RSI: 38\n\n<i>Paper trading only \u2014 not advice.</i>",
    "discord": "\ud83d\udfe2 APEX TRADE LAB Daily Signal \u2014 2026-03-24\n\nRegime: UPTREND\nAction: Light long TQQQ (16%)\n\nTQQQ: 16% | SQQQ: 0% | Cash: 84%\nNDX: 24,002 | RSI: 38\n\nPaper trading simulation \u2014 not financial advice.\n#TQQQ #SQQQ #AlgoTrading #SystematicTrading #PaperTrading"
  },
  {
    "date": "2026-03-25",
    "type": "daily",
    "generated": "2026-03-26T22:00:51.284743",
    "twitter": "\ud83d\udfe2 APEX TRADE LAB Daily Signal \u2014 2026-03-25\n\nRegime: UPTREND\nAction: Light long TQQQ (16%)\n\nTQQQ: 16% | SQQQ: 0% | Cash: 84%\nNDX: 24,163 | RSI: 42\n\nPaper trading simulation \u2014 not financial advice.\n#TQQQ #SQQQ #AlgoTrading #SystematicTrading #PaperTrading",
    "facebook": "\u26a1 APEX TRADE LAB \u2014 Daily Signal Update\n\ud83d\udcc5 2026-03-25\n\n\ud83d\udfe2 Market Regime: UPTREND\n\ud83d\udcca Action: Light long TQQQ (16%)\n\nPortfolio Allocation:\n  \u2022 TQQQ (3x Long): 16%\n  \u2022 SQQQ (3x Short): 0%\n  \u2022 Cash: 84%\n\nNDX closed at 24,163 | RSI: 42\n\nThis is a paper trading simulation for educational purposes.\nFull dashboard: [link in bio]\n\n#TQQQ #SQQQ #AlgoTrading #SystematicTrading #PaperTrading",
    "telegram": "\u26a1 <b>APEX TRADE LAB</b> \u2014 2026-03-25\n\n\ud83d\udfe2 <b>UPTREND</b>\nAction: Light long TQQQ (16%)\n\nTQQQ: 16% | SQQQ: 0% | Cash: 84%\nNDX: 24,163 | RSI: 42\n\n<i>Paper trading only \u2014 not advice.</i>",
    "discord": "\ud83d\udfe2 APEX TRADE LAB Daily Signal \u2014 2026-03-25\n\nRegime: UPTREND\nAction: Light long TQQQ (16%)\n\nTQQQ: 16% | SQQQ: 0% | Cash: 84%\nNDX: 24,163 | RSI: 42\n\nPaper trading simulation \u2014 not financial advice.\n#TQQQ #SQQQ #AlgoTrading #SystematicTrading #PaperTrading"
  },
  {
    "date": "2026-03-26",
    "type": "daily",
    "generated": "2026-03-27T23:03:10.921233",
    "twitter": "\ud83d\udfe2 APEX TRADE LAB Daily Signal \u2014 2026-03-26\n\nRegime: UPTREND\nAction: Light long TQQQ (23%)\n\nTQQQ: 23% | SQQQ: 0% | Cash: 77%\nNDX: 23,587 | RSI: 35\n\nPaper trading simulation \u2014 not financial advice.\n#TQQQ #SQQQ #AlgoTrading #SystematicTrading #PaperTrading",
    "facebook": "\u26a1 APEX TRADE LAB \u2014 Daily Signal Update\n\ud83d\udcc5 2026-03-26\n\n\ud83d\udfe2 Market Regime: UPTREND\n\ud83d\udcca Action: Light long TQQQ (23%)\n\nPortfolio Allocation:\n  \u2022 TQQQ (3x Long): 23%\n  \u2022 SQQQ (3x Short): 0%\n  \u2022 Cash: 77%\n\nNDX closed at 23,587 | RSI: 35\n\nThis is a paper trading simulation for educational purposes.\nFull dashboard: [link in bio]\n\n#TQQQ #SQQQ #AlgoTrading #SystematicTrading #PaperTrading",
    "telegram": "\u26a1 <b>APEX TRADE LAB</b> \u2014 2026-03-26\n\n\ud83d\udfe2 <b>UPTREND</b>\nAction: Light long TQQQ (23%)\n\nTQQQ: 23% | SQQQ: 0% | Cash: 77%\nNDX: 23,587 | RSI: 35\n\n<i>Paper trading only \u2014 not advice.</i>",
    "discord": "\ud83d\udfe2 APEX TRADE LAB Daily Signal \u2014 2026-03-26\n\nRegime: UPTREND\nAction: Light long TQQQ (23%)\n\nTQQQ: 23% | SQQQ: 0% | Cash: 77%\nNDX: 23,587 | RSI: 35\n\nPaper trading simulation \u2014 not financial advice.\n#TQQQ #SQQQ #AlgoTrading #SystematicTrading #PaperTrading"
  },
  {
    "date": "2026-03-27",
    "type": "weekly",
    "generated": "2026-03-27T23:03:10.921279",
    "twitter": "\ud83d\udcc9 APEX TRADE LAB \u2014 Weekly P&L\nWeek ending 2026-03-27\n\nWeekly: $-470 (-0.5%)\nTotal Return: -3.9%\nPortfolio: $96,067\nTrades this week: 4\n\nPaper trading sim \u2014 not advice.\n#TQQQ #SQQQ #AlgoTrading #SystematicTrading #PaperTrading",
    "facebook": "\ud83d\udcca APEX TRADE LAB \u2014 Weekly Performance Report\nWeek ending 2026-03-27\n\n\ud83d\udcc9 This Week: $-470 (-0.5%)\n\ud83d\udcb0 Portfolio Value: $96,067\n\ud83d\udcc8 Total Return: -3.9%\n\ud83d\udd04 Trades Executed: 4\n\nThe system traded actively this week.\n\nFull analysis: [link in bio]\n\nPaper trading simulation \u2014 educational purposes only.\n#TQQQ #SQQQ #AlgoTrading #SystematicTrading #PaperTrading",
    "telegram": "\ud83d\udcc9 APEX TRADE LAB \u2014 Weekly P&L\nWeek ending 2026-03-27\n\nWeekly: $-470 (-0.5%)\nTotal Return: -3.9%\nPortfolio: $96,067\nTrades this week: 4\n\nPaper trading sim \u2014 not advice.\n#TQQQ #SQQQ #AlgoTrading #SystematicTrading #PaperTrading",
    "discord": "\ud83d\udcc9 APEX TRADE LAB \u2014 Weekly P&L\nWeek ending 2026-03-27\n\nWeekly: $-470 (-0.5%)\nTotal Return: -3.9%\nPortfolio: $96,067\nTrades this week: 4\n\nPaper trading sim \u2014 not advice.\n#TQQQ #SQQQ #AlgoTrading #SystematicTrading #PaperTrading"
  },
  {
    "date": "2026-03-27",
    "type": "daily",
    "generated": "2026-03-30T23:07:14.981519",
    "twitter": "\ud83d\udd34 APEX TRADE LAB Daily Signal \u2014 2026-03-27\n\nRegime: DOWNTREND\nAction: CASH \u2014 no position\n\nTQQQ: 0% | SQQQ: 0% | Cash: 100%\nNDX: 23,133 | RSI: 30\n\nPaper trading simulation \u2014 not financial advice.\n#TQQQ #SQQQ #AlgoTrading #SystematicTrading #PaperTrading",
    "facebook": "\u26a1 APEX TRADE LAB \u2014 Daily Signal Update\n\ud83d\udcc5 2026-03-27\n\n\ud83d\udd34 Market Regime: DOWNTREND\n\ud83d\udcca Action: CASH \u2014 no position\n\nPortfolio Allocation:\n  \u2022 TQQQ (3x Long): 0%\n  \u2022 SQQQ (3x Short): 0%\n  \u2022 Cash: 100%\n\nNDX closed at 23,133 | RSI: 30\n\nThis is a paper trading simulation for educational purposes.\nFull dashboard: [link in bio]\n\n#TQQQ #SQQQ #AlgoTrading #SystematicTrading #PaperTrading",
    "telegram": "\u26a1 <b>APEX TRADE LAB</b> \u2014 2026-03-27\n\n\ud83d\udd34 <b>DOWNTREND</b>\nAction: CASH \u2014 no position\n\nTQQQ: 0% | SQQQ: 0% | Cash: 100%\nNDX: 23,133 | RSI: 30\n\n<i>Paper trading only \u2014 not advice.</i>",
    "discord": "\ud83d\udd34 APEX TRADE LAB Daily Signal \u2014 2026-03-27\n\nRegime: DOWNTREND\nAction: CASH \u2014 no position\n\nTQQQ: 0% | SQQQ: 0% | Cash: 100%\nNDX: 23,133 | RSI: 30\n\nPaper trading simulation \u2014 not financial advice.\n#TQQQ #SQQQ #AlgoTrading #SystematicTrading #PaperTrading"
  },
  {
    "date": "2026-03-30",
    "type": "monthly",
    "generated": "2026-03-30T23:07:14.981554",
    "twitter": "\ud83d\udcca APEX TRADE LAB \u2014 Monthly Report\n2026-03-30\n\nTotal Return: -5.3%\nCAGR: -20.8%\nSharpe: -2.18\nMax DD: -5.9%\nWin Rate: 42%\nPortfolio: $94,667\n\nFull report + live dashboard: [link]\n#TQQQ #SQQQ #AlgoTrading #SystematicTrading #PaperTrading",
    "facebook": "\ud83d\udcc8 APEX TRADE LAB \u2014 Monthly Performance Report\n\nHere is how the 7-strategy TQQQ/SQQQ system performed:\n\n\ud83d\udcb0 Portfolio: $94,667\n\ud83d\udcca Total Return: -5.3%\n\ud83d\udcc8 CAGR: -20.8%\n\u2696\ufe0f Sharpe Ratio: -2.18\n\ud83d\udcc9 Max Drawdown: -5.9%\n\ud83c\udfaf Win Rate: 42%\n\ud83d\udd04 Total Trades: 35\n\nThe system runs autonomously \u2014 making one decision at market close each day.\n\nThis is a paper trading simulation for learning systematic trading.\nFull dashboard: [link in bio]\n\n#TQQQ #SQQQ #AlgoTrading #SystematicTrading #PaperTrading",
    "telegram": "\ud83d\udcca APEX TRADE LAB \u2014 Monthly Report\n2026-03-30\n\nTotal Return: -5.3%\nCAGR: -20.8%\nSharpe: -2.18\nMax DD: -5.9%\nWin Rate: 42%\nPortfolio: $94,667\n\nFull report + live dashboard: [link]\n#TQQQ #SQQQ #AlgoTrading #SystematicTrading #PaperTrading",
    "discord": "\ud83d\udcca APEX TRADE LAB \u2014 Monthly Report\n2026-03-30\n\nTotal Return: -5.3%\nCAGR: -20.8%\nSharpe: -2.18\nMax DD: -5.9%\nWin Rate: 42%\nPortfolio: $94,667\n\nFull report + live dashboard: [link]\n#TQQQ #SQQQ #AlgoTrading #SystematicTrading #PaperTrading"
  },
  {
    "date": "2026-03-30",
    "type": "daily",
    "generated": "2026-03-31T23:02:22.576666",
    "twitter": "\ud83d\udd34 APEX TRADE LAB Daily Signal \u2014 2026-03-30\n\nRegime: DOWNTREND\nAction: CASH \u2014 no position\n\nTQQQ: 0% | SQQQ: 0% | Cash: 100%\nNDX: 22,953 | RSI: 29\n\nPaper trading simulation \u2014 not financial advice.\n#TQQQ #SQQQ #AlgoTrading #SystematicTrading #PaperTrading",
    "facebook": "\u26a1 APEX TRADE LAB \u2014 Daily Signal Update\n\ud83d\udcc5 2026-03-30\n\n\ud83d\udd34 Market Regime: DOWNTREND\n\ud83d\udcca Action: CASH \u2014 no position\n\nPortfolio Allocation:\n  \u2022 TQQQ (3x Long): 0%\n  \u2022 SQQQ (3x Short): 0%\n  \u2022 Cash: 100%\n\nNDX closed at 22,953 | RSI: 29\n\nThis is a paper trading simulation for educational purposes.\nFull dashboard: [link in bio]\n\n#TQQQ #SQQQ #AlgoTrading #SystematicTrading #PaperTrading",
    "telegram": "\u26a1 <b>APEX TRADE LAB</b> \u2014 2026-03-30\n\n\ud83d\udd34 <b>DOWNTREND</b>\nAction: CASH \u2014 no position\n\nTQQQ: 0% | SQQQ: 0% | Cash: 100%\nNDX: 22,953 | RSI: 29\n\n<i>Paper trading only \u2014 not advice.</i>",
    "discord": "\ud83d\udd34 APEX TRADE LAB Daily Signal \u2014 2026-03-30\n\nRegime: DOWNTREND\nAction: CASH \u2014 no position\n\nTQQQ: 0% | SQQQ: 0% | Cash: 100%\nNDX: 22,953 | RSI: 29\n\nPaper trading simulation \u2014 not financial advice.\n#TQQQ #SQQQ #AlgoTrading #SystematicTrading #PaperTrading"
  },
  {
    "date": "2026-03-31",
    "type": "monthly",
    "generated": "2026-03-31T23:02:22.576696",
    "twitter": "\ud83d\udcca APEX TRADE LAB \u2014 Monthly Report\n2026-03-31\n\nTotal Return: -5.3%\nCAGR: -20.1%\nSharpe: -2.16\nMax DD: -5.9%\nWin Rate: 42%\nPortfolio: $94,667\n\nFull report + live dashboard: [link]\n#TQQQ #SQQQ #AlgoTrading #SystematicTrading #PaperTrading",
    "facebook": "\ud83d\udcc8 APEX TRADE LAB \u2014 Monthly Performance Report\n\nHere is how the 7-strategy TQQQ/SQQQ system performed:\n\n\ud83d\udcb0 Portfolio: $94,667\n\ud83d\udcca Total Return: -5.3%\n\ud83d\udcc8 CAGR: -20.1%\n\u2696\ufe0f Sharpe Ratio: -2.16\n\ud83d\udcc9 Max Drawdown: -5.9%\n\ud83c\udfaf Win Rate: 42%\n\ud83d\udd04 Total Trades: 35\n\nThe system runs autonomously \u2014 making one decision at market close each day.\n\nThis is a paper trading simulation for learning systematic trading.\nFull dashboard: [link in bio]\n\n#TQQQ #SQQQ #AlgoTrading #SystematicTrading #PaperTrading",
    "telegram": "\ud83d\udcca APEX TRADE LAB \u2014 Monthly Report\n2026-03-31\n\nTotal Return: -5.3%\nCAGR: -20.1%\nSharpe: -2.16\nMax DD: -5.9%\nWin Rate: 42%\nPortfolio: $94,667\n\nFull report + live dashboard: [link]\n#TQQQ #SQQQ #AlgoTrading #SystematicTrading #PaperTrading",
    "discord": "\ud83d\udcca APEX TRADE LAB \u2014 Monthly Report\n2026-03-31\n\nTotal Return: -5.3%\nCAGR: -20.1%\nSharpe: -2.16\nMax DD: -5.9%\nWin Rate: 42%\nPortfolio: $94,667\n\nFull report + live dashboard: [link]\n#TQQQ #SQQQ #AlgoTrading #SystematicTrading #PaperTrading"
  }
]